Metadata-Version: 2.4
Name: hummingbot
Version: 20251103
Summary: Hummingbot
Home-page: https://github.com/hummingbot/hummingbot
Author: Hummingbot Foundation
Author-email: dev@hummingbot.org
License: Apache 2.0
License-File: LICENSE
Requires-Dist: aiohttp>=3.8.5
Requires-Dist: asyncssh>=2.13.2
Requires-Dist: aioprocessing>=2.0.1
Requires-Dist: aioresponses>=0.7.4
Requires-Dist: aiounittest>=1.4.2
Requires-Dist: async-timeout<5,>=4.0.2
Requires-Dist: bidict>=0.22.1
Requires-Dist: bip-utils
Requires-Dist: cachetools>=5.3.1
Requires-Dist: commlib-py>=0.11
Requires-Dist: cryptography>=41.0.2
Requires-Dist: eth-account>=0.13.0
Requires-Dist: injective-py
Requires-Dist: msgpack-python
Requires-Dist: numba>=0.61.2
Requires-Dist: numpy>=2.2.6
Requires-Dist: objgraph
Requires-Dist: pandas>=2.3.2
Requires-Dist: pandas-ta>=0.4.71b
Requires-Dist: prompt_toolkit>=3.0.39
Requires-Dist: protobuf>=4.23.3
Requires-Dist: psutil>=5.9.5
Requires-Dist: pydantic>=2
Requires-Dist: pyjwt>=2.3.0
Requires-Dist: pyperclip>=1.8.2
Requires-Dist: requests>=2.31.0
Requires-Dist: ruamel.yaml>=0.2.5
Requires-Dist: safe-pysha3
Requires-Dist: scalecodec
Requires-Dist: scipy>=1.11.1
Requires-Dist: six>=1.16.0
Requires-Dist: sqlalchemy>=1.4.49
Requires-Dist: tabulate>=0.9.0
Requires-Dist: TA-Lib>=0.6.4
Requires-Dist: tqdm>=4.67.1
Requires-Dist: ujson>=5.7.0
Requires-Dist: urllib3<2.0,>=1.26.15
Requires-Dist: web3
Requires-Dist: xrpl-py>=4.1.0
Requires-Dist: PyYaml>=0.2.5
Dynamic: author
Dynamic: author-email
Dynamic: home-page
Dynamic: license
Dynamic: license-file
Dynamic: requires-dist
Dynamic: summary
